flake8_functions/__init__.py
flake8_functions/checker.py
flake8_functions/function_arguments_amount.py
flake8_functions/function_length.py
flake8_functions/function_purity.py
flake8_functions/function_returns_amount.py
flake8_functions-0.0.8.dist-info/LICENSE
flake8_functions-0.0.8.dist-info/METADATA
flake8_functions-0.0.8.dist-info/WHEEL
flake8_functions-0.0.8.dist-info/entry_points.txt
flake8_functions-0.0.8.dist-info/top_level.txt
flake8_functions-0.0.8.dist-info/RECORD
