Metadata-Version: 2.1
Name: flake8-functions
Version: 0.0.8
Summary: A flake8 extension that checks functions
Home-page: https://github.com/best-doctor/flake8-functions
Author: Valery Pavlov
Author-email: lerikpav@gmail.com
License: MIT
Keywords: flake8
Classifier: Environment :: Console
Classifier: Framework :: Flake8
Classifier: Operating System :: OS Independent
Classifier: Topic :: Software Development :: Documentation
Classifier: Topic :: Software Development :: Libraries :: Python Modules
Classifier: Topic :: Software Development :: Quality Assurance
Classifier: Programming Language :: Python
Classifier: Programming Language :: Python :: 3.6
Classifier: Programming Language :: Python :: 3.7
Classifier: Programming Language :: Python :: 3.8
Classifier: Programming Language :: Python :: 3.9
Classifier: Programming Language :: Python :: 3.10
License-File: LICENSE
